quick_ini/__init__.py
quick_ini/quick_ini.py
quick_ini-3.2.dist-info/licenses/LICENSE
tests/__init__.py
tests/test_quickini.py
quick_ini-3.2.dist-info/METADATA
quick_ini-3.2.dist-info/WHEEL
quick_ini-3.2.dist-info/top_level.txt
quick_ini-3.2.dist-info/RECORD
