Metadata-Version: 2.4
Name: quick_ini
Version: 3.2
Summary: A library for reading from and writing to .ini formatted files
Home-page: https://github.com/olliez-mods/Quick-Ini
Author: OllieZ-Mods
Author-email: socksinthewash@gmail.com
Project-URL: Bug Reports, https://github.com/olliez-mods/Quick-Ini/issues
Project-URL: Source, https://github.com/olliez-mods/Quick-Ini
Keywords: ini config configuration parser file
Classifier: Development Status :: 4 - Beta
Classifier: Intended Audience :: Developers
Classifier: License :: OSI Approved :: MIT License
Classifier: Operating System :: OS Independent
Classifier: Programming Language :: Python :: 3
Classifier: Programming Language :: Python :: 3.7
Classifier: Programming Language :: Python :: 3.8
Classifier: Programming Language :: Python :: 3.9
Classifier: Programming Language :: Python :: 3.10
Classifier: Programming Language :: Python :: 3.11
Classifier: Programming Language :: Python :: 3.12
Requires-Python: >=3.7
License-File: LICENSE
Dynamic: author
Dynamic: author-email
Dynamic: classifier
Dynamic: description
Dynamic: description-content-type
Dynamic: home-page
Dynamic: keywords
Dynamic: license-file
Dynamic: project-url
Dynamic: requires-python
Dynamic: summary
